hurdat2parser/__init__.py
hurdat2parser/_aliases.py
hurdat2parser/_calculations.py
hurdat2parser/_future.py
hurdat2parser/_maps.py
hurdat2parser/_reports.py
hurdat2parser-2.11.dist-info/LICENSE.txt
hurdat2parser-2.11.dist-info/METADATA
hurdat2parser-2.11.dist-info/WHEEL
hurdat2parser-2.11.dist-info/top_level.txt
hurdat2parser-2.11.dist-info/RECORD
