Metadata-Version: 2.1
Name: hurdat2parser
Version: 2.11
Summary: Interpret Hurricane Data contained in HURDAT2
Home-page: http://github.com/ksgwxfan/hurdat2parser
Author: Kyle S. Gentry
Author-email: KyleSGentry@outlook.com
License: MIT
Keywords: hurricane hurdat2 meteorology weather
Classifier: Programming Language :: Python :: 3
Classifier: License :: OSI Approved :: MIT License
Classifier: Operating System :: OS Independent
Classifier: Development Status :: 5 - Production/Stable
Requires-Python: >=3.5
License-File: LICENSE.txt
Requires-Dist: pyshp
Requires-Dist: geojson
Requires-Dist: matplotlib
